{
    "135.181.210.171:4137": {
        "voting_power": 0,
        "is_validator": false,
        "moniker": "STAVR-Service",
        "network": "andromeda-1",
        "tx_index": "on",
        "earliest_block_height": 1919001,
        "latest_block_height": 1922024,
        "blocks_indexed": 1922023,
        "catching_up": false,
        "data_since": "2024-04-02T19:41:14.395399171Z"
    },
    "5.189.151.202:26677": {
        "voting_power": 0,
        "is_validator": false,
        "moniker": "AVIAONE",
        "network": "andromeda-1",
        "tx_index": "on",
        "earliest_block_height": 1920001,
        "latest_block_height": 1922023,
        "blocks_indexed": 1922022,
        "catching_up": false,
        "data_since": "2024-04-02T21:17:44.788822327Z"
    }
}