{
    "66.45.246.166:1077": {
        "voting_power": 0,
        "is_validator": false,
        "moniker": "STAVR-Service",
        "network": "planq_7070-2",
        "tx_index": "on",
        "earliest_block_height": 7818001,
        "latest_block_height": 7820284,
        "blocks_indexed": 7820283,
        "catching_up": false,
        "data_since": "2024-03-06T21:27:47.4234377Z"
    },
    "95.217.16.83:34657": {
        "voting_power": 411778,
        "is_validator": true,
        "moniker": "MONIKER",
        "network": "planq_7070-2",
        "tx_index": "on",
        "earliest_block_height": 7698001,
        "latest_block_height": 7820285,
        "blocks_indexed": 7820284,
        "catching_up": false,
        "data_since": "2024-02-28T07:25:57.544951796Z"
    },
    "65.109.35.50:20357": {
        "voting_power": 0,
        "is_validator": false,
        "moniker": "893t-agagd-asgd8asdg-d",
        "network": "planq_7070-2",
        "tx_index": "on",
        "earliest_block_height": 5067437,
        "latest_block_height": 7516700,
        "blocks_indexed": 7516699,
        "catching_up": false,
        "data_since": "2023-09-20T08:29:09.39809856Z"
    },
    "185.190.140.93:14657": {
        "voting_power": 653872,
        "is_validator": true,
        "moniker": "geonodes",
        "network": "planq_7070-2",
        "tx_index": "on",
        "earliest_block_height": 7650501,
        "latest_block_height": 7820285,
        "blocks_indexed": 7820284,
        "catching_up": false,
        "data_since": "2024-02-25T07:17:35.323314651Z"
    },
    "65.108.66.174:31657": {
        "voting_power": 0,
        "is_validator": false,
        "moniker": "hello-BccNodesRPC",
        "network": "planq_7070-2",
        "tx_index": "on",
        "earliest_block_height": 7650501,
        "latest_block_height": 7820285,
        "blocks_indexed": 7820284,
        "catching_up": false,
        "data_since": "2024-02-25T07:17:35.323314651Z"
    },
    "192.99.160.197:13657": {
        "voting_power": 0,
        "is_validator": false,
        "moniker": "BACKUP_PLANQ",
        "network": "planq_7070-2",
        "tx_index": "off",
        "earliest_block_height": 7819501,
        "latest_block_height": 7819516,
        "blocks_indexed": 7819515,
        "catching_up": true,
        "data_since": "2024-03-06T23:43:26.145217852Z"
    }
}