{
    "135.181.210.171:2077": {
        "voting_power": 0,
        "is_validator": false,
        "moniker": "STAVR-Service",
        "network": "sommelier-3",
        "tx_index": "on",
        "earliest_block_height": 12887501,
        "latest_block_height": 13045362,
        "blocks_indexed": 13045361,
        "catching_up": false,
        "data_since": "2024-01-30T14:26:21.316635567Z"
    },
    "148.113.6.121:34657": {
        "voting_power": 998912,
        "is_validator": true,
        "moniker": "Stakewolle",
        "network": "sommelier-3",
        "tx_index": "off",
        "earliest_block_height": 12151129,
        "latest_block_height": 13045361,
        "blocks_indexed": 13045360,
        "catching_up": false,
        "data_since": "2023-12-12T11:28:57.47051308Z"
    }
}