{
    "3.110.198.189:26657": {
        "voting_power": 0,
        "is_validator": false,
        "moniker": "2",
        "network": "router_9601-1",
        "tx_index": "on",
        "earliest_block_height": 11849308,
        "latest_block_height": 13215613,
        "blocks_indexed": 13215612,
        "catching_up": false,
        "data_since": "2024-04-23T12:59:10.368005317Z"
    },
    "15.206.157.168:26657": {
        "voting_power": 3320710,
        "is_validator": true,
        "moniker": "node1",
        "network": "router_9601-1",
        "tx_index": "on",
        "earliest_block_height": 13115616,
        "latest_block_height": 13215616,
        "blocks_indexed": 13215615,
        "catching_up": false,
        "data_since": "2024-05-17T05:46:59.924135983Z"
    },
    "13.235.115.79:26657": {
        "voting_power": 1197678,
        "is_validator": true,
        "moniker": "node0",
        "network": "router_9601-1",
        "tx_index": "on",
        "earliest_block_height": 13115616,
        "latest_block_height": 13215616,
        "blocks_indexed": 13215615,
        "catching_up": false,
        "data_since": "2024-05-17T05:46:59.924135983Z"
    },
    "43.205.136.8:26657": {
        "voting_power": 1338654,
        "is_validator": true,
        "moniker": "node2",
        "network": "router_9601-1",
        "tx_index": "on",
        "earliest_block_height": 13115616,
        "latest_block_height": 13215616,
        "blocks_indexed": 13215615,
        "catching_up": false,
        "data_since": "2024-05-17T05:46:59.924135983Z"
    },
    "95.217.43.26:26657": {
        "voting_power": 0,
        "is_validator": false,
        "moniker": "2",
        "network": "router_9601-1",
        "tx_index": "on",
        "earliest_block_height": 10764278,
        "latest_block_height": 13215613,
        "blocks_indexed": 13215612,
        "catching_up": false,
        "data_since": "2024-04-03T19:29:23.109978796Z"
    },
    "104.197.175.152:26657": {
        "voting_power": 0,
        "is_validator": false,
        "moniker": "2",
        "network": "router_9601-1",
        "tx_index": "on",
        "earliest_block_height": 13115615,
        "latest_block_height": 13215615,
        "blocks_indexed": 13215614,
        "catching_up": false,
        "data_since": "2024-05-17T05:46:57.610654722Z"
    },
    "136.243.88.91:3101": {
        "voting_power": 186,
        "is_validator": true,
        "moniker": "node",
        "network": "router_9601-1",
        "tx_index": "on",
        "earliest_block_height": 1548001,
        "latest_block_height": 13215613,
        "blocks_indexed": 13215612,
        "catching_up": false,
        "data_since": "2023-10-15T18:48:19.538687188Z"
    },
    "34.142.49.23:26657": {
        "voting_power": 0,
        "is_validator": false,
        "moniker": "2",
        "network": "router_9601-1",
        "tx_index": "on",
        "earliest_block_height": 13115613,
        "latest_block_height": 13215613,
        "blocks_indexed": 13215612,
        "catching_up": false,
        "data_since": "2024-05-17T05:46:54.969097434Z"
    }
}